otveti_ege/__init__.py
otveti_ege/otveti_ege.py
otveti_ege-0.0.3.dist-info/LICENSE
otveti_ege-0.0.3.dist-info/METADATA
otveti_ege-0.0.3.dist-info/WHEEL
otveti_ege-0.0.3.dist-info/top_level.txt
otveti_ege-0.0.3.dist-info/RECORD
