Metadata-Version: 2.1
Name: otveti-ege
Version: 0.0.3
Summary: Shows answers from ege.sdamgia.ru
Author-email: BlueSpy <alexej.rutskij@gmail.com>
License: MIT License        
Project-URL: Homepage, https://github.com/LLEECCHH/otveti-ege
Project-URL: Bug Tracker, https://github.com/LLEECCHH/otveti-ege/issues
Classifier: Programming Language :: Python :: 3
Classifier: License :: OSI Approved :: MIT License
Classifier: Operating System :: OS Independent
Requires-Python: >=3.7
License-File: LICENSE
